safep/AFEP_parse.py
safep/TI.py
safep/__init__.py
safep/estimators.py
safep/fileIO.py
safep/helpers.py
safep/plotting.py
safep/processing.py
safep-0.1.4.dist-info/licenses/LICENSE
safep-0.1.4.dist-info/METADATA
safep-0.1.4.dist-info/WHEEL
safep-0.1.4.dist-info/top_level.txt
safep-0.1.4.dist-info/RECORD
