Metadata-Version: 2.4
Name: safep
Version: 0.1.4
Summary: Tools for Analyzing and Debugging (SA)FEP calculations
Author-email: Brannigan Lab <grace.brannigan@rutgers.edu>
Project-URL: Homepage, https://github.com/BranniganLab/safep
Project-URL: Issues, https://github.com/BranniganLab/safep/issues
Classifier: Development Status :: 4 - Beta
Classifier: Intended Audience :: Science/Research
Classifier: Operating System :: POSIX :: Linux
Classifier: Programming Language :: Python :: 3.12
Classifier: License :: OSI Approved :: GNU General Public License v3 or later (GPLv3+)
Classifier: Operating System :: OS Independent
Requires-Python: >=3.10
License-File: LICENSE
Requires-Dist: numpy>=1.22.0
Requires-Dist: pandas>=1.4.0
Requires-Dist: alchemlyb==2.0.0
Requires-Dist: matplotlib>=3.5.0
Requires-Dist: natsort>=7.1.0
Requires-Dist: tqdm
Dynamic: license-file
